reiz/__init__.py
reiz/audio.py
reiz/cue.py
reiz/marker.py
reiz/time.py
reiz/visual.py
reiz/_audio/__init__.py
reiz/_audio/fft.py
reiz/_audio/noise.py
reiz/_audio/primitives.py
reiz/_audio/tts.py
reiz/_marker/__init__.py
reiz/_marker/__main__.py
reiz/_marker/client.py
reiz/_marker/mitm.py
reiz/_marker/safeguard.py
reiz/_visual/__init__.py
reiz/_visual/_primitives.py
reiz/_visual/_screen.py
reiz/_visual/colors.py
reiz/_visual/complex.py
reiz/data/logo.png
reiz/examples/__init__.py
reiz/examples/basic.py
Reiz-3.5.1.dist-info/METADATA
Reiz-3.5.1.dist-info/WHEEL
Reiz-3.5.1.dist-info/entry_points.txt
Reiz-3.5.1.dist-info/top_level.txt
Reiz-3.5.1.dist-info/RECORD
