Metadata-Version: 2.1
Name: Reiz
Version: 3.5.1
Summary: A Python toolbox for visual and auditory stimulation based on pyglet and pylsl.
Home-page: https://github.com/pyreiz/pyreiz
Author: Robert Guggenberger
Author-email: robert.guggenberger@uni-tuebingen.de
License: MIT
Download-URL: https://github.com/pyreiz/pyreiz.git
Platform: UNKNOWN
Classifier: Development Status :: 5 - Production/Stable
Classifier: Environment :: Console
Classifier: Intended Audience :: Developers
Classifier: Intended Audience :: Science/Research
Classifier: License :: OSI Approved :: MIT License
Classifier: Operating System :: OS Independent
Classifier: Programming Language :: Python :: 3.6
Classifier: Programming Language :: Python :: 3.7
Classifier: Programming Language :: Python :: 3.8
Classifier: Topic :: Multimedia :: Graphics :: Presentation
Classifier: Topic :: Multimedia :: Sound/Audio :: Players
Classifier: Topic :: Scientific/Engineering :: Human Machine Interfaces
Classifier: Topic :: Scientific/Engineering :: Medical Science Apps.
Requires-Dist: pyglet (>=1.5)
Requires-Dist: pylsl (>=1.13)
Provides-Extra: tts
Requires-Dist: pyttsx3 (>=2.7) ; extra == 'tts'
